Metadata-Version: 1.0
Name: basicutilsd
Version: 1.0.0
Summary: Basic helper functions
Home-page: https://github.com/rohit-taneja/basicutilsd
Author: Rohit Taneja
Author-email: rohit.or.taneja@gmail.com
License: UNKNOWN
Platform: UNKNOWN
